calibrate.py
calibrate-0.10.0.dist-info/DESCRIPTION.rst
calibrate-0.10.0.dist-info/METADATA
calibrate-0.10.0.dist-info/RECORD
calibrate-0.10.0.dist-info/WHEEL
calibrate-0.10.0.dist-info/metadata.json
calibrate-0.10.0.dist-info/top_level.txt
calibrate-0.10.0.dist-info/zip-safe
